README.md
setup.cfg
setup.py
PyPIOMAS/Functions.py
PyPIOMAS/PyPIOMAS.py
PyPIOMAS/__init__.py
PyPIOMAS.egg-info/PKG-INFO
PyPIOMAS.egg-info/SOURCES.txt
PyPIOMAS.egg-info/dependency_links.txt
PyPIOMAS.egg-info/requires.txt
PyPIOMAS.egg-info/top_level.txt