Metadata-Version: 1.0
Name: PyPIOMAS
Version: 0.1.2
Summary: A package for downloading and converting the PIOMAS dataset
Home-page: https://github.com/Weiming-Hu/PyPIOMAS
Author: Weiming Hu
Author-email: weiming@psu.edu
License: LICENSE
Platform: UNKNOWN
